MongoSchemaImportExport-0.2.4.data/scripts/mongo-schema-export.py
MongoSchemaImportExport-0.2.4.data/scripts/mongo-schema-import.py
MongoSchemaImportExport-0.2.4.dist-info/METADATA
MongoSchemaImportExport-0.2.4.dist-info/RECORD
MongoSchemaImportExport-0.2.4.dist-info/WHEEL
MongoSchemaImportExport-0.2.4.dist-info/top_level.txt
mongo_import_export_schema/__init__.py
mongo_import_export_schema/mongo-schema-export.py
mongo_import_export_schema/mongo-schema-import.py
