Metadata-Version: 2.1
Name: MongoSchemaImportExport
Version: 0.2.4
Summary: Import and export metadata about mongodb databases and collections
Home-page: https://github.com/jonnoftw/mongo_import_export_schema
Author: Jonathan Mackenzie
License: Creative Commons Attribution-Noncommercial-Share Alike license
Keywords: pymongo mongodb schema import export
Platform: UNKNOWN
Classifier: Programming Language :: Python
Requires: pymongo
